[
  {
    "specialty": "Anesthesiology (Pain) Specialist in Pabna",
    "url": "https://www.doctorbangladesh.com/anesthesiologist-pabna/"
  },
  {
    "specialty": "Cancer Specialist in Pabna",
    "url": "https://www.doctorbangladesh.com/oncologist-pabna/"
  },
  {
    "specialty": "Cardiac Surgery Specialist in Pabna",
    "url": "https://www.doctorbangladesh.com/cardiac-surgeon-pabna/"
  },
  {
    "specialty": "Cardiology Specialist in Pabna",
    "url": "https://www.doctorbangladesh.com/cardiologist-pabna/"
  },
  {
    "specialty": "Chest & Asthma Specialist in Pabna",
    "url": "https://www.doctorbangladesh.com/chest-specialist-pabna/"
  },
  {
    "specialty": "Child Specialist in Pabna",
    "url": "https://www.doctorbangladesh.com/pediatrician-pabna/"
  },
  {
    "specialty": "Colorectal Surgery Specialist in Pabna",
    "url": "https://www.doctorbangladesh.com/colorectal-surgeon-pabna/"
  },
  {
    "specialty": "Dental Specialist in Pabna",
    "url": "https://www.doctorbangladesh.com/dentist-pabna/"
  },
  {
    "specialty": "Diabetes & Hormone Specialist in Pabna",
    "url": "https://www.doctorbangladesh.com/endocrinologist-pabna/"
  },
  {
    "specialty": "ENT Specialist in Pabna",
    "url": "https://www.doctorbangladesh.com/otolaryngologist-pabna/"
  },
  {
    "specialty": "Eye Specialist in Pabna",
    "url": "https://www.doctorbangladesh.com/ophthalmologist-pabna/"
  },
  {
    "specialty": "Gastroenterology Specialist in Pabna",
    "url": "https://www.doctorbangladesh.com/gastroenterologist-pabna/"
  },
  {
    "specialty": "General & Laparoscopic Surgery Specialist in Pabna",
    "url": "https://www.doctorbangladesh.com/general-surgeon-pabna/"
  },
  {
    "specialty": "Gynecology & Obstetrics Specialist in Pabna",
    "url": "https://www.doctorbangladesh.com/gynecologist-pabna/"
  },
  {
    "specialty": "Hematology (Blood) Specialist in Pabna",
    "url": "https://www.doctorbangladesh.com/hematologist-pabna/"
  },
  {
    "specialty": "Infertility Specialist in Pabna",
    "url": "https://www.doctorbangladesh.com/infertility-specialist-pabna/"
  },
  {
    "specialty": "Kidney Specialist in Pabna",
    "url": "https://www.doctorbangladesh.com/nephrologist-pabna/"
  },
  {
    "specialty": "Liver Specialist in Pabna",
    "url": "https://www.doctorbangladesh.com/hepatologist-pabna/"
  },
  {
    "specialty": "Medicine Specialist in Pabna",
    "url": "https://www.doctorbangladesh.com/medicine-specialist-pabna/"
  },
  {
    "specialty": "Neurology/Neuromedicine Specialist in Pabna",
    "url": "https://www.doctorbangladesh.com/neurologist-pabna/"
  },
  {
    "specialty": "Neurosurgery Specialist in Pabna",
    "url": "https://www.doctorbangladesh.com/neurosurgeon-pabna/"
  },
  {
    "specialty": "Orthopedic Specialist in Pabna",
    "url": "https://www.doctorbangladesh.com/orthopedic-specialist-pabna/"
  },
  {
    "specialty": "Pediatric Surgery Specialist in Pabna",
    "url": "https://www.doctorbangladesh.com/pediatric-surgeon-pabna/"
  },
  {
    "specialty": "Physical Medicine Specialist in Pabna",
    "url": "https://www.doctorbangladesh.com/physical-medicine-specialist-pabna/"
  },
  {
    "specialty": "Plastic Surgery Specialist in Pabna",
    "url": "https://www.doctorbangladesh.com/plastic-surgeon-pabna/"
  },
  {
    "specialty": "Psychiatry (Mental) Specialist in Pabna",
    "url": "https://www.doctorbangladesh.com/psychiatrist-pabna/"
  },
  {
    "specialty": "Rheumatology Specialist in Pabna",
    "url": "https://www.doctorbangladesh.com/rheumatologist-pabna/"
  },
  {
    "specialty": "Sex Specialist in Pabna",
    "url": "https://www.doctorbangladesh.com/sexologist-pabna/"
  },
  {
    "specialty": "Skin Specialist in Pabna",
    "url": "https://www.doctorbangladesh.com/dermatologist-pabna/"
  },
  {
    "specialty": "Urology Specialist in Pabna",
    "url": "https://www.doctorbangladesh.com/urologist-pabna/"
  },
  {
    "specialty": "Vascular Surgery Specialist in Pabna",
    "url": "https://www.doctorbangladesh.com/vascular-surgeon-pabna/"
  }
]